JavaBianmaGuifan/README.md
JavaBianmaGuifan/__init__.py
JavaBianmaGuifan/__main__.py
JavaBianmaGuifan/file.epub
JavaBianmaGuifan/index.html
JavaBianmaGuifan/css/__init__.py
JavaBianmaGuifan/css/annotations.css
JavaBianmaGuifan/css/main.css
JavaBianmaGuifan/css/normalize.css
JavaBianmaGuifan/css/popup.css
JavaBianmaGuifan/font/__init__.py
JavaBianmaGuifan/font/fontello.eot
JavaBianmaGuifan/font/fontello.svg
JavaBianmaGuifan/font/fontello.ttf
JavaBianmaGuifan/font/fontello.woff
JavaBianmaGuifan/img/__init__.py
JavaBianmaGuifan/img/annotator-glyph-sprite.png
JavaBianmaGuifan/img/annotator-icon-sprite.png
JavaBianmaGuifan/img/apple-touch-icon.png
JavaBianmaGuifan/img/cancelfullscreen.png
JavaBianmaGuifan/img/close.png
JavaBianmaGuifan/img/fullscreen.png
JavaBianmaGuifan/img/loader.gif
JavaBianmaGuifan/img/menu-icon.png
JavaBianmaGuifan/img/save.png
JavaBianmaGuifan/img/saved.png
JavaBianmaGuifan/img/settings-s.png
JavaBianmaGuifan/img/settings.png
JavaBianmaGuifan/img/star.png
JavaBianmaGuifan/js/__init__.py
JavaBianmaGuifan/js/epub.js
JavaBianmaGuifan/js/epub.min.js
JavaBianmaGuifan/js/epub.min.map
JavaBianmaGuifan/js/hooks.min.js
JavaBianmaGuifan/js/hooks.min.map
JavaBianmaGuifan/js/reader.js
JavaBianmaGuifan/js/reader.js.map
JavaBianmaGuifan/js/reader.min.js
JavaBianmaGuifan/js/reader.min.map
JavaBianmaGuifan/js/hooks/__init__.py
JavaBianmaGuifan/js/hooks/extensions/__init__.py
JavaBianmaGuifan/js/hooks/extensions/highlight.js
JavaBianmaGuifan/js/libs/__init__.py
JavaBianmaGuifan/js/libs/jquery.min.js
JavaBianmaGuifan/js/libs/localforage.min.js
JavaBianmaGuifan/js/libs/screenfull.js
JavaBianmaGuifan/js/libs/screenfull.min.js
JavaBianmaGuifan/js/libs/zip.min.js
JavaBianmaGuifan/js/plugins/__init__.py
JavaBianmaGuifan/js/plugins/hypothesis.js
JavaBianmaGuifan/js/plugins/search.js
java_bianma_guifan-2024.3.2.0.dist-info/METADATA
java_bianma_guifan-2024.3.2.0.dist-info/WHEEL
java_bianma_guifan-2024.3.2.0.dist-info/entry_points.txt
java_bianma_guifan-2024.3.2.0.dist-info/top_level.txt
java_bianma_guifan-2024.3.2.0.dist-info/RECORD
